{
  "enabled": true,
  "logs": [
    {
      "sender": "260966566253",
      "action": "viewed",
      "timestamp": 1766907347991
    },
    {
      "sender": "254724455112",
      "action": "viewed",
      "timestamp": 1766907483155
    },
    {
      "sender": "254724455112",
      "action": "viewed",
      "timestamp": 1766907487733
    },
    {
      "sender": "254724455112",
      "action": "viewed",
      "timestamp": 1766907490265
    },
    {
      "sender": "254724455112",
      "action": "viewed",
      "timestamp": 1766907494356
    },
    {
      "sender": "254724455112",
      "action": "viewed",
      "timestamp": 1766907496879
    },
    {
      "sender": "254724455112",
      "action": "viewed",
      "timestamp": 1766907498535
    },
    {
      "sender": "254797373671",
      "action": "viewed",
      "timestamp": 1766907507635
    },
    {
      "sender": "23233406747",
      "action": "viewed",
      "timestamp": 1766907674041
    },
    {
      "sender": "254117013133",
      "action": "viewed",
      "timestamp": 1766907695345
    },
    {
      "sender": "23233406747",
      "action": "viewed",
      "timestamp": 1766907758661
    },
    {
      "sender": "260765200301",
      "action": "viewed",
      "timestamp": 1766907844345
    },
    {
      "sender": "254743121515",
      "action": "viewed",
      "timestamp": 1766907884218
    },
    {
      "sender": "254112614820",
      "action": "viewed",
      "timestamp": 1766907965743
    },
    {
      "sender": "260967415240",
      "action": "viewed",
      "timestamp": 1766907973180
    },
    {
      "sender": "254768638925",
      "action": "viewed",
      "timestamp": 1766907976950
    },
    {
      "sender": "2348155931801",
      "action": "viewed",
      "timestamp": 1766908038165
    },
    {
      "sender": "255615667337",
      "action": "viewed",
      "timestamp": 1766908041289
    },
    {
      "sender": "254768638925",
      "action": "viewed",
      "timestamp": 1766908096647
    },
    {
      "sender": "254752589553",
      "action": "viewed",
      "timestamp": 1766908108763
    },
    {
      "sender": "260966566253",
      "action": "viewed",
      "timestamp": 1766908119255
    },
    {
      "sender": "254734971054",
      "action": "viewed",
      "timestamp": 1766908212937
    },
    {
      "sender": "254793544290",
      "action": "viewed",
      "timestamp": 1766908250922
    },
    {
      "sender": "260760157870",
      "action": "viewed",
      "timestamp": 1766908278358
    },
    {
      "sender": "260760157870",
      "action": "viewed",
      "timestamp": 1766908380240
    },
    {
      "sender": "254112614820",
      "action": "viewed",
      "timestamp": 1766908545763
    },
    {
      "sender": "255653028085",
      "action": "viewed",
      "timestamp": 1766908655513
    },
    {
      "sender": "254112537667",
      "action": "viewed",
      "timestamp": 1766908662570
    },
    {
      "sender": "254753879768",
      "action": "viewed",
      "timestamp": 1766908867575
    },
    {
      "sender": "255653028085",
      "action": "viewed",
      "timestamp": 1766909023625
    },
    {
      "sender": "255653028085",
      "action": "viewed",
      "timestamp": 1766909031993
    },
    {
      "sender": "255653028085",
      "action": "viewed",
      "timestamp": 1766909035793
    },
    {
      "sender": "255653028085",
      "action": "viewed",
      "timestamp": 1766909038935
    },
    {
      "sender": "255653028085",
      "action": "viewed",
      "timestamp": 1766909042354
    },
    {
      "sender": "255653028085",
      "action": "viewed",
      "timestamp": 1766909046349
    },
    {
      "sender": "254115076372",
      "action": "viewed",
      "timestamp": 1766909098308
    },
    {
      "sender": "260777021831",
      "action": "viewed",
      "timestamp": 1766909099418
    },
    {
      "sender": "254115076372",
      "action": "viewed",
      "timestamp": 1766909111968
    },
    {
      "sender": "260964830720",
      "action": "viewed",
      "timestamp": 1766909224873
    },
    {
      "sender": "260964830720",
      "action": "viewed",
      "timestamp": 1766909313502
    },
    {
      "sender": "260774874667",
      "action": "viewed",
      "timestamp": 1766909324251
    },
    {
      "sender": "254722745701",
      "action": "viewed",
      "timestamp": 1766909423066
    },
    {
      "sender": "254722745701",
      "action": "viewed",
      "timestamp": 1766909428280
    },
    {
      "sender": "260774874667",
      "action": "viewed",
      "timestamp": 1766909445252
    },
    {
      "sender": "260967415240",
      "action": "viewed",
      "timestamp": 1766909560658
    },
    {
      "sender": "260774874667",
      "action": "viewed",
      "timestamp": 1766909593130
    },
    {
      "sender": "254742272267",
      "action": "viewed",
      "timestamp": 1766909713957
    },
    {
      "sender": "254108413522",
      "action": "viewed",
      "timestamp": 1766909829327
    },
    {
      "sender": "260767076220",
      "action": "viewed",
      "timestamp": 1766909897034
    },
    {
      "sender": "254728640349",
      "action": "viewed",
      "timestamp": 1766910075378
    },
    {
      "sender": "254728640349",
      "action": "viewed",
      "timestamp": 1766910080148
    },
    {
      "sender": "254724455112",
      "action": "viewed",
      "timestamp": 1766910083292
    },
    {
      "sender": "254115076372",
      "action": "viewed",
      "timestamp": 1766910091835
    },
    {
      "sender": "254115076372",
      "action": "viewed",
      "timestamp": 1766910101405
    },
    {
      "sender": "254768188297",
      "action": "viewed",
      "timestamp": 1766910114146
    },
    {
      "sender": "254742272267",
      "action": "viewed",
      "timestamp": 1766910116079
    },
    {
      "sender": "254768188297",
      "action": "viewed",
      "timestamp": 1766910132467
    },
    {
      "sender": "254768188297",
      "action": "viewed",
      "timestamp": 1766910146543
    },
    {
      "sender": "254768188297",
      "action": "viewed",
      "timestamp": 1766910161254
    },
    {
      "sender": "254116217770",
      "action": "viewed",
      "timestamp": 1766910175722
    },
    {
      "sender": "260966566253",
      "action": "viewed",
      "timestamp": 1766910314476
    },
    {
      "sender": "260966566253",
      "action": "viewed",
      "timestamp": 1766910316554
    },
    {
      "sender": "254784766028",
      "action": "viewed",
      "timestamp": 1766910373298
    },
    {
      "sender": "254768188297",
      "action": "viewed",
      "timestamp": 1766910377193
    },
    {
      "sender": "254720015560",
      "action": "viewed",
      "timestamp": 1766910423201
    },
    {
      "sender": "254798820507",
      "action": "viewed",
      "timestamp": 1766910439698
    },
    {
      "sender": "254720015560",
      "action": "viewed",
      "timestamp": 1766910440878
    },
    {
      "sender": "254720015560",
      "action": "viewed",
      "timestamp": 1766910513396
    },
    {
      "sender": "254702858465",
      "action": "viewed",
      "timestamp": 1766910521155
    },
    {
      "sender": "254784766028",
      "action": "viewed",
      "timestamp": 1766910546274
    },
    {
      "sender": "254768188297",
      "action": "viewed",
      "timestamp": 1766910809859
    },
    {
      "sender": "254769460582",
      "action": "viewed",
      "timestamp": 1766910847215
    },
    {
      "sender": "254769460582",
      "action": "viewed",
      "timestamp": 1766910850895
    },
    {
      "sender": "260962347198",
      "action": "viewed",
      "timestamp": 1766910903783
    },
    {
      "sender": "260760157870",
      "action": "viewed",
      "timestamp": 1766910934091
    },
    {
      "sender": "260779291415",
      "action": "viewed",
      "timestamp": 1766911050103
    },
    {
      "sender": "260765200301",
      "action": "viewed",
      "timestamp": 1766911116007
    },
    {
      "sender": "254115606707",
      "action": "viewed",
      "timestamp": 1766911179392
    },
    {
      "sender": "260760157870",
      "action": "viewed",
      "timestamp": 1766911232698
    },
    {
      "sender": "254794390185",
      "action": "viewed",
      "timestamp": 1766911234461
    },
    {
      "sender": "254113118246",
      "action": "viewed",
      "timestamp": 1766911384934
    },
    {
      "sender": "254768188297",
      "action": "viewed",
      "timestamp": 1766911397152
    },
    {
      "sender": "254742272267",
      "action": "viewed",
      "timestamp": 1766911600478
    },
    {
      "sender": "260970496737",
      "action": "viewed",
      "timestamp": 1766911731856
    },
    {
      "sender": "254713076215",
      "action": "viewed",
      "timestamp": 1766911796722
    },
    {
      "sender": "254108413522",
      "action": "viewed",
      "timestamp": 1766911802447
    },
    {
      "sender": "254703397679",
      "action": "viewed",
      "timestamp": 1766911826586
    },
    {
      "sender": "254796291679",
      "action": "viewed",
      "timestamp": 1766911831594
    },
    {
      "sender": "254740938228",
      "action": "viewed",
      "timestamp": 1766911836453
    },
    {
      "sender": "254748138295",
      "action": "viewed",
      "timestamp": 1766911837811
    },
    {
      "sender": "254740938228",
      "action": "viewed",
      "timestamp": 1766911839289
    },
    {
      "sender": "254748138295",
      "action": "viewed",
      "timestamp": 1766911841664
    },
    {
      "sender": "254740938228",
      "action": "viewed",
      "timestamp": 1766911845231
    },
    {
      "sender": "254748138295",
      "action": "viewed",
      "timestamp": 1766911847447
    },
    {
      "sender": "254748138295",
      "action": "viewed",
      "timestamp": 1766911850976
    },
    {
      "sender": "254740938228",
      "action": "viewed",
      "timestamp": 1766911854527
    },
    {
      "sender": "254740938228",
      "action": "viewed",
      "timestamp": 1766911857324
    },
    {
      "sender": "254740938228",
      "action": "viewed",
      "timestamp": 1766911860184
    },
    {
      "sender": "254740938228",
      "action": "viewed",
      "timestamp": 1766911862978
    },
    {
      "sender": "254740938228",
      "action": "viewed",
      "timestamp": 1766911865831
    }
  ],
  "totalViewed": 621,
  "lastViewed": {
    "sender": "254740938228",
    "action": "viewed",
    "timestamp": 1766911865831
  },
  "consecutiveViews": 5,
  "lastSender": "254740938228",
  "settings": {
    "rateLimitDelay": 1000,
    "viewToAll": true,
    "ignoreConsecutiveLimit": true,
    "markAsSeen": true,
    "noHourlyLimit": true
  }
}